cort/__init__.py
cort/analysis/__init__.py
cort/analysis/data_structures.py
cort/analysis/error_extractors.py
cort/analysis/plotting.py
cort/analysis/spanning_tree_algorithms.py
cort/analysis/visualization.py
cort/analysis/visualization/style.css
cort/analysis/visualization/lib/cort-for-raw.js
cort/analysis/visualization/lib/cort.js
cort/analysis/visualization/lib/jquery-2.1.1.min.js
cort/analysis/visualization/lib/jquery.jsPlumb-1.6.4.js
cort/config_files/corenlp.ini
cort/config_files/corenlp_with_coref.ini
cort/core/__init__.py
cort/core/corpora.py
cort/core/documents.py
cort/core/external_data.py
cort/core/head_finders.py
cort/core/mention_extractor.py
cort/core/mention_property_computer.py
cort/core/mentions.py
cort/core/mixins.py
cort/core/singletons.py
cort/core/spans.py
cort/core/util.py
cort/coreference/__init__.py
cort/coreference/clusterer.py
cort/coreference/cost_functions.py
cort/coreference/experiments.py
cort/coreference/features.py
cort/coreference/instance_extractors.py
cort/coreference/perceptrons.pyx
cort/coreference/approaches/__init__.py
cort/coreference/approaches/antecedent_trees.py
cort/coreference/approaches/mention_pairs.py
cort/coreference/approaches/mention_ranking.py
cort/coreference/multigraph/__init__.py
cort/coreference/multigraph/decoders.py
cort/coreference/multigraph/features.py
cort/coreference/multigraph/multigraphs.py
cort/coreference/multigraph/weighting_functions.py
cort/preprocessing/__init__.py
cort/preprocessing/pipeline.py
cort/reference-coreference-scorers/v8.01/README.txt
cort/reference-coreference-scorers/v8.01/scorer.bat
cort/reference-coreference-scorers/v8.01/scorer.pl
cort/reference-coreference-scorers/v8.01/lib/CorScorer.pm
cort/reference-coreference-scorers/v8.01/lib/Cwd.pm
cort/reference-coreference-scorers/v8.01/lib/Algorithm/Munkres.pm
cort/reference-coreference-scorers/v8.01/lib/Algorithm/README.Munkres
cort-0.2.4.5.dist-info/DESCRIPTION.rst
cort-0.2.4.5.dist-info/METADATA
cort-0.2.4.5.dist-info/RECORD
cort-0.2.4.5.dist-info/WHEEL
cort-0.2.4.5.dist-info/metadata.json
cort-0.2.4.5.dist-info/top_level.txt
