Metadata-Version: 2.0
Name: cort
Version: 0.2.4.5
Summary: A coreference resolution research toolkit.
Home-page: http://github.com/smartschat/cort
Author: Sebastian Martschat, Thierry Goeckel, Patrick Claus
Author-email: sebastian.martschat@gmail.com
License: MIT
Keywords: NLP,CL,natural language processing,computational linguistics,coreference resolution,text analytics
Platform: UNKNOWN
Classifier: Intended Audience :: Science/Research
Classifier: Programming Language :: Python :: 2.7
Classifier: Programming Language :: Python :: 3.3
Classifier: Topic :: Scientific/Engineering
Classifier: Topic :: Scientific/Engineering :: Artificial Intelligence
Classifier: Topic :: Text Processing
Requires-Dist: beautifulsoup4
Requires-Dist: cython
Requires-Dist: future
Requires-Dist: jpype1
Requires-Dist: matplotlib
Requires-Dist: mmh3
Requires-Dist: nltk (>=3.0.1)
Requires-Dist: numpy
Requires-Dist: pystanforddependencies (>=0.3.1)
